[
  {
    "id": 1,
    "name": "彩虹屁",
    "desc": "Colorful - 彩虹屁",
    "key": "a",
    "created_at": "2020-11-21T22:36:54.000Z",
    "updated_at": "2020-11-21T22:36:54.000Z",
    "path": "./sentences/a.json"
  },
  {
    "id": 2,
    "name": "坏话",
    "desc": "bad - 坏话",
    "key": "b",
    "created_at": "2020-11-21T22:36:54.000Z",
    "updated_at": "2020-11-21T22:36:54.000Z",
    "path": "./sentences/b.json"
  },
  {
    "id": 3,
    "name": "客观",
    "desc": "keguan - 客观",
    "key": "c",
    "created_at": "2020-11-21T22:36:54.000Z",
    "updated_at": "2020-11-21T22:36:54.000Z",
    "path": "./sentences/c.json"
  }
]